{
  "main": {
    "id": "65ba8edb78d1ebb7",
    "type": "split",
    "children": [
      {
        "id": "449af21d3cc32614",
        "type": "tabs",
        "children": [
          {
            "id": "9384a2460d4b3356",
            "type": "leaf",
            "state": {
              "type": "markdown",
              "state": {
                "file": "docs/usage/component.mdx",
                "mode": "source",
                "backlinks": false,
                "source": true
              }
            }
          }
        ]
      }
    ],
    "direction": "vertical"
  },
  "left": {
    "id": "e2722a070f1a0547",
    "type": "split",
    "children": [
      {
        "id": "07c0c6739863be3b",
        "type": "tabs",
        "children": [
          {
            "id": "18ccc24f397c34c6",
            "type": "leaf",
            "state": {
              "type": "file-explorer",
              "state": {
                "sortOrder": "byCreatedTime"
              }
            }
          },
          {
            "id": "2e36ac7e9959beea",
            "type": "leaf",
            "state": {
              "type": "search",
              "state": {
                "query": "",
                "matchingCase": true,
                "explainSearch": false,
                "collapseAll": false,
                "extraContext": false,
                "sortOrder": "alphabetical"
              }
            }
          },
          {
            "id": "4a8aec1205104702",
            "type": "leaf",
            "state": {
              "type": "starred",
              "state": {}
            }
          },
          {
            "id": "fae60baeea003170",
            "type": "leaf",
            "state": {
              "type": "bookmarks",
              "state": {}
            }
          }
        ]
      }
    ],
    "direction": "horizontal",
    "width": 341.5
  },
  "right": {
    "id": "465428516897b8dc",
    "type": "split",
    "children": [
      {
        "id": "d86ab136f127d4d9",
        "type": "tabs",
        "children": [
          {
            "id": "e8b4d292e43e09fb",
            "type": "leaf",
            "state": {
              "type": "advanced-tables-toolbar",
              "state": {}
            }
          },
          {
            "id": "eed2a0b3816eafab",
            "type": "leaf",
            "state": {
              "type": "all-properties",
              "state": {
                "sortOrder": "frequency",
                "showSearch": false,
                "searchQuery": ""
              }
            }
          }
        ]
      }
    ],
    "direction": "horizontal",
    "width": 300,
    "collapsed": true
  },
  "left-ribbon": {
    "hiddenItems": {
      "switcher:Open quick switcher": false,
      "graph:Open graph view": false,
      "command-palette:Open command palette": false,
      "table-editor-obsidian:Advanced Tables Toolbar": false,
      "obsidian-excalidraw-plugin:Create new drawing": false
    }
  },
  "active": "9384a2460d4b3356",
  "lastOpenFiles": [
    "build/ko/assets/js/main.c134de4c.js",
    "build/ko/assets/js/runtime~main.094a96de.js",
    "build/ko/assets/js/main.c134de4c.js.LICENSE.txt",
    "build/ko/assets/js/f4f34a3a.bcb36f8e.js",
    "build/ko/assets/js/ed2d995c.502fbaa4.js",
    "build/ko/assets/js/e273c56f.b1bd5e6f.js",
    "build/ko/assets/js/dcad1dc8.ef2242e6.js",
    "build/ko/assets/js/d9f32620.d20ba0c8.js",
    "build/ko/assets/js/ccc49370.e7a3b8d3.js",
    "build/ko/assets/js/b6eb1aa2.4b775e60.js",
    "build/ko/assets/js/b24931aa.1a046904.js",
    "build/ko/assets/images/docusaurus-plushie-banner-a60f7593abca1e3eef26a9afa244e4fb.jpeg",
    "build/img/undraw_docusaurus_tree.svg",
    "build/img/undraw_docusaurus_react.svg",
    "build/img/undraw_docusaurus_mountain.svg",
    "build/img/ogimage.png",
    "build/img/logo.svg",
    "build/img/docusaurus.png",
    "build/img/docusaurus-social-card.jpg",
    "build/assets/images/docusaurus-plushie-banner-a60f7593abca1e3eef26a9afa244e4fb.jpeg",
    "build/ko/img/undraw_docusaurus_tree.svg",
    "i18n/ko/docusaurus-plugin-content-docs/current/usage/create-a-page.md",
    "docs/usage/create-a-page.md",
    "i18n/ko/docusaurus-plugin-content-docs/current/tutorial-basics/deploy-your-site.md",
    "i18n/ko/docusaurus-plugin-content-docs/current/tutorial-basics/create-a-page.md",
    "i18n/ko/docusaurus-plugin-content-docs/current/tutorial-basics/create-a-document.md",
    "i18n/ko/docusaurus-plugin-content-docs/current/tutorial-basics/create-a-blog-post.md",
    "i18n/ko/docusaurus-plugin-content-docs/current/tutorial-basics/congratulations.md",
    "i18n/ko/docusaurus-plugin-content-docs/current/intro.mdx.md",
    "Excalidraw/Draw.md",
    "web/element-event.md",
    "flutter/dart-extension-types.md",
    "().md",
    "flutter/dart-code-generation.md",
    "flutter/flutter-review-1.md",
    "flutter/flutter-web-interop.md",
    "number-theory/number-theory-7-3.md",
    "number-theory/number-theory-7-2.md",
    "number-theory/number-theory-5-3.md",
    "number-theory/number-theory-6-4.md",
    "boj/boj-27498.md",
    "boj/boj-28139.md",
    "boj/boj-28703.md",
    "boj/-boj-24422.md",
    "boj/-boj-12345.md",
    "boj/-boj-123.md",
    "Untitled.canvas"
  ]
}